LICENSE
README.md
setup.py
SolidsOpt.egg-info/PKG-INFO
SolidsOpt.egg-info/SOURCES.txt
SolidsOpt.egg-info/dependency_links.txt
SolidsOpt.egg-info/requires.txt
SolidsOpt.egg-info/top_level.txt
solidsopt/__init__.py
solidsopt/models.py
solidsopt/optimize.py
solidsopt/Utils/__init__.py
solidsopt/Utils/beams.py
solidsopt/Utils/solver.py