Metadata-Version: 2.1
Name: SolidsOpt
Version: 0.1
Summary: This package is made to perfome topology optimization of 2D solids
Home-page: https://github.com/kssgarcia/SolidsOpt
Author: Kevin Sepúlveda-García <kssepulveg@eafit.edu.co>, Nicolas Guarin-Zapata <nguarinz@eafit.edu.co>
Author-email: kssepulveg@eafit.edu.co
License: MIT
Keywords: finite-elements,scientific-computing,deep learning,topology,optimization
Classifier: Development Status :: 4 - Beta
Classifier: Intended Audience :: Education
Classifier: Topic :: Scientific/Engineering
Classifier: License :: OSI Approved :: MIT License
Classifier: Programming Language :: Python :: 3
License-File: LICENSE
Requires-Dist: numpy
Requires-Dist: scipy
Requires-Dist: matplotlib
Requires-Dist: easygui
Requires-Dist: meshio==3.0
Requires-Dist: tensorflow==2.15.0
Requires-Dist: solidspy
